AUTHORS
COPYING
LICENSE
MANIFEST.in
README.md
setup.py
BWP.egg-info/PKG-INFO
BWP.egg-info/SOURCES.txt
BWP.egg-info/dependency_links.txt
BWP.egg-info/not-zip-safe
BWP.egg-info/requires.txt
BWP.egg-info/top_level.txt
bwp/__bwp__.py
bwp/__init__.py
bwp/apps.py
bwp/conf.py
bwp/forms.py
bwp/models.py
bwp/sites.py
bwp/tests.py
bwp/urls.py
bwp/validation.py
bwp/views.py
bwp/widgets.py
bwp/contrib/__init__.py
bwp/contrib/abstracts/__init__.py
bwp/contrib/abstracts/models.py
bwp/contrib/abstracts/locale/ru/LC_MESSAGES/django.mo
bwp/contrib/abstracts/locale/ru/LC_MESSAGES/django.po
bwp/contrib/contacts/__bwp__.py
bwp/contrib/contacts/__init__.py
bwp/contrib/contacts/apps.py
bwp/contrib/contacts/models.py
bwp/contrib/contacts/locale/ru/LC_MESSAGES/django.mo
bwp/contrib/contacts/locale/ru/LC_MESSAGES/django.po
bwp/contrib/devices/__bwp__.py
bwp/contrib/devices/__init__.py
bwp/contrib/devices/apps.py
bwp/contrib/devices/cron_spooler_device.py
bwp/contrib/devices/exceptions.py
bwp/contrib/devices/models.py
bwp/contrib/devices/remote.py
bwp/contrib/devices/drivers/__init__.py
bwp/contrib/devices/drivers/helpers.py
bwp/contrib/devices/drivers/ICPDAS/__init__.py
bwp/contrib/devices/drivers/ICPDAS/conf.py
bwp/contrib/devices/drivers/ICPDAS/dcon.py
bwp/contrib/devices/drivers/ICPDAS/helpers.py
bwp/contrib/devices/drivers/ShtrihM/__init__.py
bwp/contrib/devices/drivers/Zonerich/__init__.py
bwp/contrib/devices/locale/ru/LC_MESSAGES/django.mo
bwp/contrib/devices/locale/ru/LC_MESSAGES/django.po
bwp/contrib/devices/management/__init__.py
bwp/contrib/devices/management/commands/__init__.py
bwp/contrib/devices/management/commands/spooler_device.py
bwp/contrib/devices/migrations/0001_initial.py
bwp/contrib/devices/migrations/__init__.py
bwp/contrib/qualifiers/__bwp__.py
bwp/contrib/qualifiers/__init__.py
bwp/contrib/qualifiers/apps.py
bwp/contrib/qualifiers/models.py
bwp/contrib/qualifiers/fixtures/non_auto_initial_data.json
bwp/contrib/qualifiers/locale/ru/LC_MESSAGES/django.mo
bwp/contrib/qualifiers/locale/ru/LC_MESSAGES/django.po
bwp/contrib/qualifiers/migrations/0001_initial.py
bwp/contrib/qualifiers/migrations/__init__.py
