Metadata-Version: 1.1
Name: BWP
Version: 0.7.0
Summary: The Business Web Platform is Django-application. Contains models, templates and other preparations for the fast building of ERP system
Home-page: https://bitbucket.org/rosix/bwp/
Author: Grigoriy Kramarenko
Author-email: root@rosix.ru
License: GNU General Public License v3 or later (GPLv3+)
Platform: any
Classifier: Development Status :: 3 - Alpha
Classifier: Environment :: Web Environment
Classifier: Framework :: Django
Classifier: Intended Audience :: Developers
Classifier: License :: OSI Approved :: GNU General Public License v3 or later (GPLv3+)
Classifier: Natural Language :: Russian
Classifier: Operating System :: OS Independent
Classifier: Programming Language :: JavaScript
Classifier: Programming Language :: Python
Classifier: Topic :: Internet :: WWW/HTTP :: Dynamic Content
Classifier: Topic :: Internet :: WWW/HTTP :: Site Management
Classifier: Topic :: Office/Business
